[
    {
        "login":  "alexey-goloburdin",
        "id":  1895747,
        "node_id":  "MDQ6VXNlcjE4OTU3NDc=",
        "avatar_url":  "https://avatars.githubusercontent.com/u/1895747?v=4",
        "gravatar_id":  "",
        "url":  "https://api.github.com/users/alexey-goloburdin",
        "html_url":  "https://github.com/alexey-goloburdin",
        "followers_url":  "https://api.github.com/users/alexey-goloburdin/followers",
        "following_url":  "https://api.github.com/users/alexey-goloburdin/following{/other_user}",
        "gists_url":  "https://api.github.com/users/alexey-goloburdin/gists{/gist_id}",
        "starred_url":  "https://api.github.com/users/alexey-goloburdin/starred{/owner}{/repo}",
        "subscriptions_url":  "https://api.github.com/users/alexey-goloburdin/subscriptions",
        "organizations_url":  "https://api.github.com/users/alexey-goloburdin/orgs",
        "repos_url":  "https://api.github.com/users/alexey-goloburdin/repos",
        "events_url":  "https://api.github.com/users/alexey-goloburdin/events{/privacy}",
        "received_events_url":  "https://api.github.com/users/alexey-goloburdin/received_events",
        "type":  "User",
        "user_view_type":  "public",
        "site_admin":  false,
        "score":  1.0
    },
    {
        "login":  "tkhirianov",
        "id":  1845971,
        "node_id":  "MDQ6VXNlcjE4NDU5NzE=",
        "avatar_url":  "https://avatars.githubusercontent.com/u/1845971?v=4",
        "gravatar_id":  "",
        "url":  "https://api.github.com/users/tkhirianov",
        "html_url":  "https://github.com/tkhirianov",
        "followers_url":  "https://api.github.com/users/tkhirianov/followers",
        "following_url":  "https://api.github.com/users/tkhirianov/following{/other_user}",
        "gists_url":  "https://api.github.com/users/tkhirianov/gists{/gist_id}",
        "starred_url":  "https://api.github.com/users/tkhirianov/starred{/owner}{/repo}",
        "subscriptions_url":  "https://api.github.com/users/tkhirianov/subscriptions",
        "organizations_url":  "https://api.github.com/users/tkhirianov/orgs",
        "repos_url":  "https://api.github.com/users/tkhirianov/repos",
        "events_url":  "https://api.github.com/users/tkhirianov/events{/privacy}",
        "received_events_url":  "https://api.github.com/users/tkhirianov/received_events",
        "type":  "User",
        "user_view_type":  "public",
        "site_admin":  false,
        "score":  1.0
    },
    {
        "login":  "KEV0143",
        "id":  76757946,
        "node_id":  "MDQ6VXNlcjc2NzU3OTQ2",
        "avatar_url":  "https://avatars.githubusercontent.com/u/76757946?v=4",
        "gravatar_id":  "",
        "url":  "https://api.github.com/users/KEV0143",
        "html_url":  "https://github.com/KEV0143",
        "followers_url":  "https://api.github.com/users/KEV0143/followers",
        "following_url":  "https://api.github.com/users/KEV0143/following{/other_user}",
        "gists_url":  "https://api.github.com/users/KEV0143/gists{/gist_id}",
        "starred_url":  "https://api.github.com/users/KEV0143/starred{/owner}{/repo}",
        "subscriptions_url":  "https://api.github.com/users/KEV0143/subscriptions",
        "organizations_url":  "https://api.github.com/users/KEV0143/orgs",
        "repos_url":  "https://api.github.com/users/KEV0143/repos",
        "events_url":  "https://api.github.com/users/KEV0143/events{/privacy}",
        "received_events_url":  "https://api.github.com/users/KEV0143/received_events",
        "type":  "User",
        "user_view_type":  "public",
        "site_admin":  false,
        "score":  1.0
    },
    {
        "login":  "klen",
        "id":  90699,
        "node_id":  "MDQ6VXNlcjkwNjk5",
        "avatar_url":  "https://avatars.githubusercontent.com/u/90699?v=4",
        "gravatar_id":  "",
        "url":  "https://api.github.com/users/klen",
        "html_url":  "https://github.com/klen",
        "followers_url":  "https://api.github.com/users/klen/followers",
        "following_url":  "https://api.github.com/users/klen/following{/other_user}",
        "gists_url":  "https://api.github.com/users/klen/gists{/gist_id}",
        "starred_url":  "https://api.github.com/users/klen/starred{/owner}{/repo}",
        "subscriptions_url":  "https://api.github.com/users/klen/subscriptions",
        "organizations_url":  "https://api.github.com/users/klen/orgs",
        "repos_url":  "https://api.github.com/users/klen/repos",
        "events_url":  "https://api.github.com/users/klen/events{/privacy}",
        "received_events_url":  "https://api.github.com/users/klen/received_events",
        "type":  "User",
        "user_view_type":  "public",
        "site_admin":  false,
        "score":  1.0
    },
    {
        "login":  "chip-red-pill",
        "id":  65568749,
        "node_id":  "MDQ6VXNlcjY1NTY4NzQ5",
        "avatar_url":  "https://avatars.githubusercontent.com/u/65568749?v=4",
        "gravatar_id":  "",
        "url":  "https://api.github.com/users/chip-red-pill",
        "html_url":  "https://github.com/chip-red-pill",
        "followers_url":  "https://api.github.com/users/chip-red-pill/followers",
        "following_url":  "https://api.github.com/users/chip-red-pill/following{/other_user}",
        "gists_url":  "https://api.github.com/users/chip-red-pill/gists{/gist_id}",
        "starred_url":  "https://api.github.com/users/chip-red-pill/starred{/owner}{/repo}",
        "subscriptions_url":  "https://api.github.com/users/chip-red-pill/subscriptions",
        "organizations_url":  "https://api.github.com/users/chip-red-pill/orgs",
        "repos_url":  "https://api.github.com/users/chip-red-pill/repos",
        "events_url":  "https://api.github.com/users/chip-red-pill/events{/privacy}",
        "received_events_url":  "https://api.github.com/users/chip-red-pill/received_events",
        "type":  "User",
        "user_view_type":  "public",
        "site_admin":  false,
        "score":  1.0
    }
]